<?xml version="1.0" encoding="UTF-8"?>
<persistence version="1.0" xmlns="http://java.sun.com/xml/ns/persistence" xmlns:xsi="http://www.w3.org/2001/XMLSchema-instance" xsi:schemaLocation="http://java.sun.com/xml/ns/persistence http://java.sun.com/xml/ns/persistence/persistence_1_0.xsd">
  <persistence-unit name="ProyectoFinalPU" transaction-type="RESOURCE_LOCAL">
    <provider>org.eclipse.persistence.jpa.PersistenceProvider</provider>
    <class>ec.edu.ups.modelo.ClienteFijo</class>
    <class>ec.edu.ups.modelo.Egresos</class>
    <class>ec.edu.ups.modelo.Espacios</class>
    <class>ec.edu.ups.modelo.FacturaClienteFijo</class>
    <class>ec.edu.ups.modelo.FacturaClienteM</class>
    <class>ec.edu.ups.modelo.TicketClienteMomentaneo</class>
    <class>ec.edu.ups.modelo.HistorialClientesFijos</class>
    <class>ec.edu.ups.modelo.HistorialTickets</class>
    <class>ec.edu.ups.modelo.Ingresos</class>
    <class>ec.edu.ups.modelo.Tarifa</class>
    <class>ec.edu.ups.modelo.Usuario</class>
    <properties>
      <property name="eclipselink.jdbc.url" value="jdbc:postgresql://localhost:5432/postgres"/>
      <property name="eclipselink.jdbc.user" value="postgres"/>
      <property name="eclipselink.jdbc.password" value="123"/>
      <property name="eclipselink.jdbc.driver" value="org.postgresql.Driver"/>
      <property name="eclipselink.ddl-generation" value="create-tables"/>
    </properties>
  </persistence-unit>
</persistence>
